openpulse/__init__.py
openpulse/ast.py
openpulse/parser.py
openpulse/printer.py
openpulse/py.typed
openpulse/spec.py
openpulse/_antlr/__init__.py
openpulse/_antlr/_4_10/openpulseLexer.interp
openpulse/_antlr/_4_10/openpulseLexer.py
openpulse/_antlr/_4_10/openpulseLexer.tokens
openpulse/_antlr/_4_10/openpulseParser.interp
openpulse/_antlr/_4_10/openpulseParser.py
openpulse/_antlr/_4_10/openpulseParser.tokens
openpulse/_antlr/_4_10/openpulseParserListener.py
openpulse/_antlr/_4_10/openpulseParserVisitor.py
openpulse/_antlr/_4_11/openpulseLexer.interp
openpulse/_antlr/_4_11/openpulseLexer.py
openpulse/_antlr/_4_11/openpulseLexer.tokens
openpulse/_antlr/_4_11/openpulseParser.interp
openpulse/_antlr/_4_11/openpulseParser.py
openpulse/_antlr/_4_11/openpulseParser.tokens
openpulse/_antlr/_4_11/openpulseParserListener.py
openpulse/_antlr/_4_11/openpulseParserVisitor.py
openpulse/_antlr/_4_12/openpulseLexer.interp
openpulse/_antlr/_4_12/openpulseLexer.py
openpulse/_antlr/_4_12/openpulseLexer.tokens
openpulse/_antlr/_4_12/openpulseParser.interp
openpulse/_antlr/_4_12/openpulseParser.py
openpulse/_antlr/_4_12/openpulseParser.tokens
openpulse/_antlr/_4_12/openpulseParserListener.py
openpulse/_antlr/_4_12/openpulseParserVisitor.py
openpulse/_antlr/_4_13/openpulseLexer.interp
openpulse/_antlr/_4_13/openpulseLexer.py
openpulse/_antlr/_4_13/openpulseLexer.tokens
openpulse/_antlr/_4_13/openpulseParser.interp
openpulse/_antlr/_4_13/openpulseParser.py
openpulse/_antlr/_4_13/openpulseParser.tokens
openpulse/_antlr/_4_13/openpulseParserListener.py
openpulse/_antlr/_4_13/openpulseParserVisitor.py
openpulse/_antlr/_4_7/openpulseLexer.interp
openpulse/_antlr/_4_7/openpulseLexer.py
openpulse/_antlr/_4_7/openpulseLexer.tokens
openpulse/_antlr/_4_7/openpulseParser.interp
openpulse/_antlr/_4_7/openpulseParser.py
openpulse/_antlr/_4_7/openpulseParser.tokens
openpulse/_antlr/_4_7/openpulseParserListener.py
openpulse/_antlr/_4_7/openpulseParserVisitor.py
openpulse-1.0.1.dist-info/METADATA
openpulse-1.0.1.dist-info/WHEEL
openpulse-1.0.1.dist-info/top_level.txt
openpulse-1.0.1.dist-info/RECORD
