Metadata-Version: 2.1
Name: openpulse
Version: 1.0.1
Summary: Reference OpenPulse AST in Python
Home-page: https://github.com/openqasm/openpulse/
Author: OpenQASM Contributors
License: Apache 2.0 Software License
Keywords: openqasm quantum openpulse
Classifier: License :: OSI Approved :: Apache Software License
Classifier: Intended Audience :: Developers
Classifier: Intended Audience :: Science/Research
Classifier: Operating System :: Microsoft :: Windows
Classifier: Operating System :: MacOS
Classifier: Operating System :: POSIX :: Linux
Classifier: Programming Language :: Python :: 3 :: Only
Classifier: Topic :: Scientific/Engineering
Requires-Dist: antlr4_python3_runtime<4.14,>=4.7
Requires-Dist: importlib_metadata; python_version < "3.10"
Requires-Dist: openqasm3[parser]<2.0,>=1.0.0
Provides-Extra: tests
Requires-Dist: pytest>=6.0; extra == "tests"
Requires-Dist: pyyaml; extra == "tests"
Provides-Extra: all
Requires-Dist: pytest>=6.0; extra == "all"
Requires-Dist: pyyaml; extra == "all"
